odoo/addons/hr_attendance_overtime/README.rst
odoo/addons/hr_attendance_overtime/__init__.py
odoo/addons/hr_attendance_overtime/__manifest__.py
odoo/addons/hr_attendance_overtime/post_install.py
odoo/addons/hr_attendance_overtime/data/hr_attendance_reason.xml
odoo/addons/hr_attendance_overtime/i18n/es.po
odoo/addons/hr_attendance_overtime/i18n/fr.po
odoo/addons/hr_attendance_overtime/i18n/hr_attendance_overtime.pot
odoo/addons/hr_attendance_overtime/i18n/it.po
odoo/addons/hr_attendance_overtime/models/__init__.py
odoo/addons/hr_attendance_overtime/models/hr_attendance.py
odoo/addons/hr_attendance_overtime/models/hr_attendance_reason.py
odoo/addons/hr_attendance_overtime/models/hr_employee.py
odoo/addons/hr_attendance_overtime/models/resource.py
odoo/addons/hr_attendance_overtime/readme/CONFIGURE.rst
odoo/addons/hr_attendance_overtime/readme/CONTRIBUTORS.rst
odoo/addons/hr_attendance_overtime/readme/DESCRIPTION.rst
odoo/addons/hr_attendance_overtime/readme/ROADMAP.rst
odoo/addons/hr_attendance_overtime/static/description/icon.png
odoo/addons/hr_attendance_overtime/static/description/index.html
odoo/addons/hr_attendance_overtime/static/img/my_attendance.png
odoo/addons/hr_attendance_overtime/static/src/js/hr_attendance_overtime.js
odoo/addons/hr_attendance_overtime/static/src/xml/attendance.xml
odoo/addons/hr_attendance_overtime/static/tests/hr_attendance_overtime_tests.js
odoo/addons/hr_attendance_overtime/tests/__init__.py
odoo/addons/hr_attendance_overtime/tests/test_attendance_overtime.py
odoo/addons/hr_attendance_overtime/views/assets.xml
odoo/addons/hr_attendance_overtime/views/hr_attendance_reason_view.xml
odoo/addons/hr_attendance_overtime/views/hr_attendance_view.xml
odoo/addons/hr_attendance_overtime/views/resource_view.xml
odoo14_addon_hr_attendance_overtime-14.0.1.0.1.dist-info/METADATA
odoo14_addon_hr_attendance_overtime-14.0.1.0.1.dist-info/WHEEL
odoo14_addon_hr_attendance_overtime-14.0.1.0.1.dist-info/top_level.txt
odoo14_addon_hr_attendance_overtime-14.0.1.0.1.dist-info/RECORD
