Metadata-Version: 2.1
Name: odoo14-addon-hr_attendance_overtime
Version: 14.0.1.0.1
Summary: Mark Attendances as overtime.
Home-page: https://github.com/OCA/hr-attendance
Author: Pierre Verkest, Odoo Community Association (OCA)
Author-email: support@odoo-community.org
License: AGPL-3
Classifier: Programming Language :: Python
Classifier: Framework :: Odoo
Classifier: Framework :: Odoo :: 14.0
Classifier: License :: OSI Approved :: GNU Affero General Public License v3
Requires-Python: >=3.6
Requires-Dist: odoo14-addon-hr-attendance-autoclose
Requires-Dist: odoo14-addon-hr-attendance-reason
Requires-Dist: odoo<14.1dev,>=14.0a
